scalaps/__init__.py
scalaps-0.0.3.dist-info/LICENSE
scalaps-0.0.3.dist-info/METADATA
scalaps-0.0.3.dist-info/WHEEL
scalaps-0.0.3.dist-info/top_level.txt
scalaps-0.0.3.dist-info/RECORD
