Metadata-Version: 2.1
Name: scalaps
Version: 0.0.3
Summary: Scala-inspired data structures for Python
Home-page: https://github.com/matthagy/scalaps
Author: Matt Hagy
Author-email: matthew.hagy@gmail.com
License: UNKNOWN
Platform: UNKNOWN
Classifier: Programming Language :: Python :: 3
Classifier: License :: OSI Approved :: MIT License
Classifier: Operating System :: OS Independent
